<?xml version="1.0" encoding="UTF-8"?>
<!-- Generated with VCD-db Translator (http://vcddb.konni.com/translator) -->
<!-- To update or create a new language, use the online translator! -->
<!-- Original Author: Rodrigo P. Telles -->
<language>
	<id>pt_BR</id>
	<name>Brazilian Portuguese</name>
	<charset>UTF-8</charset>
	<strings>


		<!-- Language specific keys -->
		<string id="language.type">BR</string>
		<string id="language.name">Brazilian Portuguese</string>
		<string id="language.charset">UTF-8</string>


		<!-- user menu keys -->
		<string id="menu.mine">Meu menu</string>
		<string id="menu.settings">Minhas configurações</string>
		<string id="menu.movies">Meus filmes</string>
		<string id="menu.addmovie">Adicionar novo filme</string>
		<string id="menu.loansystem">Sistema de empréstimo</string>
		<string id="menu.wishlist">Minha lista de desejos</string>
		<string id="menu.categories">Categorias de filmes</string>
		<string id="menu.rss">Meus Feeds RSS</string>
		<string id="menu.controlpanel">Painel de Controle</string>
		<string id="menu.register">Registrar</string>
		<string id="menu.logout">Sair</string>
		<string id="menu.submit">Enviar</string>
		<string id="menu.topusers">Usuários Top</string>
		<string id="menu.wishlistpublic">Outras listas de desejos</string>
		<string id="menu.statistics">Estatísticas</string>


		<!-- login based strings -->
		<string id="login.login">Login</string>
		<string id="login.username">Usuário</string>
		<string id="login.password">Senha</string>
		<string id="login.remember">Lembre-me</string>
		<string id="login.info">Deixe vazio se &lt;b&gt;não&lt;/b&gt; deseja alterar sua senha</string>


		<!-- Register based strings -->
		<string id="register.title">Registro</string>
		<string id="register.fullname">Nome completo</string>
		<string id="register.email">Email</string>
		<string id="register.again">Senha novamente</string>
		<string id="register.disabled">Desculpe, o Administrador desabilitou novas inscrições no momento</string>
		<string id="register.ok">Registro completado com sucesso, agora você pode logar-se no VCD-db.</string>


		<!-- strings for user properties -->
		<string id="userproperties.notify">Me enviar um e-mail quando um novo filme for adicionado?</string>
		<string id="userproperties.show_adult">Mostra conteúdo adulto no site?</string>
		<string id="userproperties.rss">Permitir feeds RSS da minha lista de filmes?</string>
		<string id="userproperties.wishlist">Permitir que outros vejam a minha lista de desejos?</string>
		<string id="userproperties.use_index">Utilizar campos do número de índice para ID's de mídias customizadas?</string>
		<string id="userproperties.seen_list">Manter-me a par dos filmes que eu já vi?</string>
		<string id="userproperties.playoption">Utilizar opções de playback do cliente?</string>
		<string id="userproperties.nfo">Habilitar arquivos NFO?</string>
		<string id="userproperties.default_image">Exibir imagens por padrão</string>


		<!-- strings for user settings -->
		<string id="usersettings.player">Configurações do tocador</string>
		<string id="usersettings.ownfeed">Ver meus feeds</string>
		<string id="usersettings.custom">Customizar minha página principal</string>
		<string id="usersettings.showstat">Mostrar estatísticas</string>
		<string id="usersettings.showside">Mostrar novos filmes na coluna lateral</string>
		<string id="usersettings.selectrss">Selecionar feeds RSS</string>
		<string id="usersettings.pagelook">Layout Web</string>
		<string id="usersettings.pagemode">Selecionar template padrão:</string>
		<string id="usersettings.updated">Informação do usuário atualizada</string>
		<string id="usersettings.update_failed">Falha a atualização</string>
		<string id="usersettings.list">Lista de ignorados</string>
		<string id="usersettings.desc">Ignorar todos os filmes dos seguintes usuários:</string>


		<!-- strings for search and search results -->
		<string id="search.search">Pesquisar</string>
		<string id="search.title">Por título</string>
		<string id="search.actor">Por ator</string>
		<string id="search.director">Por diretor</string>
		<string id="search.results">Resultados da pesquisa</string>
		<string id="search.extended">Pesquisa detalhada</string>
		<string id="search.noresult">A pesquisa não retornou resultados</string>


		<!-- strings for movie categories -->
		<string id="category.action">Ação</string>
		<string id="category.adult">Adulto</string>
		<string id="category.adventure">Aventura</string>
		<string id="category.animation">Animação</string>
		<string id="category.anime">Anime / Manga</string>
		<string id="category.comedy">Comédia</string>
		<string id="category.crime">Crime</string>
		<string id="category.documentary">Documentário</string>
		<string id="category.drama">Drama</string>
		<string id="category.family">Família</string>
		<string id="category.fantasy">Fantasia</string>
		<string id="category.filmnoir">Filme Noir</string>
		<string id="category.horror">Terror</string>
		<string id="category.jamesbond">James Bond</string>
		<string id="category.musicvideo">Vídeo Musical</string>
		<string id="category.musical">Musical</string>
		<string id="category.mystery">Mistério</string>
		<string id="category.romance">Romance</string>
		<string id="category.scifi">Ficção Científica</string>
		<string id="category.short">Curta</string>
		<string id="category.thriller">Suspense</string>
		<string id="category.tvshows">Shows de TV</string>
		<string id="category.war">Guerra</string>
		<string id="category.western">Faroeste</string>
		<string id="category.xrated">X-Rated</string>


		<!-- movie specific strings -->
		<string id="movie.movie">O Filme</string>
		<string id="movie.actors">Atores</string>
		<string id="movie.category">Categoria</string>
		<string id="movie.year">Ano de produção</string>
		<string id="movie.copies">Cópias</string>
		<string id="movie.from">De</string>
		<string id="movie.title">Título</string>
		<string id="movie.alttitle">Título alternativo</string>
		<string id="movie.grade">Classificação</string>
		<string id="movie.director">Diretor</string>
		<string id="movie.country">País de produção</string>
		<string id="movie.runtime">Duração</string>
		<string id="movie.minutes">minutos</string>
		<string id="movie.plot">Sinopse</string>
		<string id="movie.noplot">Sinopse não disponível</string>
		<string id="movie.covers">Capas de CD</string>
		<string id="movie.available">Cópias disponíveis</string>
		<string id="movie.media">Mídia</string>
		<string id="movie.num">Número de CD's</string>
		<string id="movie.date">Data de adição</string>
		<string id="movie.owner">Proprietário</string>
		<string id="movie.noactors">Lista de atores não disponível</string>
		<string id="movie.info">Informação sobre o filme</string>
		<string id="movie.details">Detalhes da minha cópia</string>
		<string id="movie.mediatype">Tipo de mídia</string>
		<string id="movie.comment">Comentário</string>
		<string id="movie.private">Marcar como privado?</string>
		<string id="movie.screenshots">Imagens do filme</string>
		<string id="movie.noscreens">Imagens do filme não disponíveis</string>
		<string id="movie.show">Mostrar</string>
		<string id="movie.hide">Esconder</string>
		<string id="movie.change">Alterar informações</string>
		<string id="movie.nocovers">Capas de CD não disponíveis</string>
		<string id="movie.bycat">Títulos por categoria</string>
		<string id="movie.currcat">Categoria atual</string>
		<string id="movie.textview">Visão em texto</string>
		<string id="movie.imageview">Visão em imagens</string>
		<string id="movie.mineonly">Mostrar somente meus filmes</string>
		<string id="movie.similar">Filmes similares</string>
		<string id="movie.mediaindex">Índex de mídias</string>


		<!-- IMDB specific strings -->
		<string id="imdb.details">Detalhes IMDB</string>
		<string id="imdb.plot">Resumo da Sinopse</string>
		<string id="imdb.gallery">Galeria de Fotos</string>
		<string id="imdb.trailers">Trailers</string>
		<string id="imdb.links">Links IMDB</string>
		<string id="imdb.not">Informações IMDB não disponíveis</string>


		<!-- DVD specific string -->
		<string id="dvd.region">Região</string>
		<string id="dvd.format">Formato</string>
		<string id="dvd.aspect">Formato de tela</string>
		<string id="dvd.audio">Áudio</string>
		<string id="dvd.subtitles">Legendas</string>


		<!-- My movies page strings -->
		<string id="mymovies.export">Exportar dados</string>
		<string id="mymovies.excel">Exportar para Excel</string>
		<string id="mymovies.xml">Exportar para XML</string>
		<string id="mymovies.xmlthumbs">Exportar miniaturas para XML</string>
		<string id="mymovies.actions">Minhas ações</string>
		<string id="mymovies.join">Junção de disco</string>
		<string id="mymovies.joinmovies">Junção de discos de filmes</string>
		<string id="mymovies.joinsuser">Selecionar usuário</string>
		<string id="mymovies.joinsmedia">Selecionar tipo de mídia</string>
		<string id="mymovies.joinscat">Selecionar categoria</string>
		<string id="mymovies.joinstype">Selecionar ação</string>
		<string id="mymovies.joinshow">Mostrar resultados</string>
		<string id="mymovies.noresults">A consulta não retornou resultados</string>
		<string id="mymovies.textall">Visão de Impressão (Modo Texto)</string>
		<string id="mymovies.pwall">Visão de Impressão (Todos)</string>
		<string id="mymovies.pwmovies">Visão de Impressão (Filmes)</string>
		<string id="mymovies.pwtv">Visão de Impressão (Shows de TV)</string>
		<string id="mymovies.pwblue">Visão de Impressão (Filmes Azuis)</string>
		<string id="mymovies.j1">Filmes que eu possuo mas o usuário não</string>
		<string id="mymovies.j2">Filmes que o usuário possui mas eu não</string>
		<string id="mymovies.j3">Filmes que ambos possuímos</string>
		<string id="mymovies.overview">Visão geral da coleção</string>
		<string id="mymovies.info">Nesta página você pode encontrar tudo sobre os meus filmes.&lt;BR/&gt;À direita, estão ações que você pode executar na sua coleção de filmes.&lt;BR/&gt;Você também pode exportar sua lista em formato Excel para impressão ou utilizar as funções XML para backup ou para mover os dados da sua coleção de um VCD-db para outro VCD-db.</string>
		<string id="mymovies.keys">Editar ID's customizados</string>
		<string id="mymovies.seenlist">Editar lista de filmes já vistos</string>
		<string id="mymovies.helppicker">Escolha um filme para assistir</string>
		<string id="mymovies.helppickerinfo">Não sabe o que assistir esta noite?&lt;BR/&gt;Deixe o VCD-db ajudá-lo a encontrar um filme.&lt;BR/&gt;Você pode opcionalmente criar filtros e utilizá-los para limitar as seleções sugeridas pelo VCD-db.</string>
		<string id="mymovies.find">Encontrar um filme</string>
		<string id="mymovies.notseen">Sugerir apenas filmes que eu ainda não assistí</string>
		<string id="mymovies.friends">Meus amigos que pedem CD's emprestados</string>


		<!-- strings for the movie manager window -->
		<string id="manager.basic">Informações básicas</string>
		<string id="manager.imdb">Informações IMDB</string>
		<string id="manager.empire">Informações DVDEmpire</string>
		<string id="manager.copy">Minha cópia</string>
		<string id="manager.copies">Minhas cópias</string>
		<string id="manager.nocopy">Você não tem cópias</string>
		<string id="manager.1copy">Cópia</string>
		<string id="manager.addact">Adicionar atores</string>
		<string id="manager.addtodb">Adicionar novos atores ao DB</string>
		<string id="manager.savetodb">Salvar no DB</string>
		<string id="manager.savetodbncd">Salvar no DB e no filme</string>
		<string id="manager.indb">Atores na base de dados</string>
		<string id="manager.sel">Atores selecionados</string>
		<string id="manager.stars">Estrelas</string>
		<string id="manager.browse">Navegar por localização de arquivo</string>
		<string id="manager.addmedia">Adicionar...</string>


		<!-- Add new movie based strings -->
		<string id="addmovie.info">Selecione um método para adicionar novo filme</string>
		<string id="addmovie.imdb">Trazer da Base de dados de Filmes da Internet</string>
		<string id="addmovie.imdbtitle">Entre palavras chaves para procurar</string>
		<string id="addmovie.manual">Entrar dados manualmente</string>
		<string id="addmovie.listed">Adicionar filmes já listados</string>
		<string id="addmovie.xml">Adicionar filmes a partir de arquivo XML exportado</string>
		<string id="addmovie.xmlfile">Selecione o arquivo XML para importar</string>
		<string id="addmovie.xmlnote">(Aviso, somente arquivos XML que tenham sido exportados pelo VCD-db podem ser utilizados para importar seus filmes aquí.&lt;br/&gt;Você pode exportar seus filmes a partir da sessão &quot;Meus filmes&quot; Você deve evitar editar manualmente arquivos XML exportados.)</string>
		<string id="addmovie.maxfilesize">Tamanho máximo do arquivo</string>
		<string id="addmovie.dvdempire">Trazer de Adult DVD Empire (Filmes X-rated)</string>
		<string id="addmovie.listedstep1">Passo 1&lt;br/&gt;Selecione os títulos que você quer adicionar à sua lista.&lt;br/&gt;Você pode selecionar o tipo de mídia no próximo passo.</string>
		<string id="addmovie.listedstep2">Passo 2.&lt;br/&gt;Selecione o tipo de mídia apropriado.</string>
		<string id="addmovie.indb">Filmes em VCD-DB</string>
		<string id="addmovie.selected">Títulos selecionados</string>
		<string id="addmovie.infolist">Dê duplo clique sobre o título para selecioná-lo ou utilize as setas.&lt;br/&gt;Você pode utilizar o teclado para encontrar os títulos rapidamente.</string>
		<string id="addmovie.notitles">Nenhum outro usuário adicionou filmes no VCD-db</string>


		<!-- strings for XML actions -->
		<string id="xml.confirm">Confirmar upload de arquivo XML</string>
		<string id="xml.contains">Arquivo XML contem %d filmes.</string>
		<string id="xml.info1">Pressione confirme para processar os filmes e salvá-los na base de dados. Ou pressine cancelar para abortar.</string>
		<string id="xml.info2">Se você deseja incluir thumbnails (posters) dos filmes que você está prestes a importar do arquivo XML, você &lt;b&gt;PRECISA&lt;/b&gt; ter o arquivo XML de thumbnails agora!.&lt;br/&gt;&lt;br/&gt;Posters não podem ser importados após você ter finalizado a importação dos filmes a partir do arquivo XML corrente.&lt;br/&gt;Se você ainda tem o arquivo XML de thumbnails disponível, marque o campo abaixo e no próximo passo, após importar seus filmes da lista abaixo, você será questionado a submeter seu arquivo XML de thumbnails para processamento.</string>
		<string id="xml.thumbnails">Inserir miniaturas a partir do meu arquivo XML de miniaturas</string>
		<string id="xml.list">Lista completa de filmes encontrados no arquivo XML.</string>
		<string id="xml.error">Nenhum título encontrado no arquivo XML.&lt;br/&gt;O arquivo pode estar danificado ou simplesmente vazio.&lt;br/&gt;&lt;br/&gt;Tenha certeza de que você está utilizando um arquivo XML que foi exportado pelo VCD-db...</string>
		<string id="xml.results">Resultado do upload de arquivo XML.</string>
		<string id="xml.results2">Aquí está o resultado da sua importação XML.&lt;br/&gt;Total de %d filmes foram importados.</string>


		<!-- strings for DVD empire based fetch -->
		<string id="dvdempire.info">Informações de AdultDVDEmpire.com ....</string>
		<string id="dvdempire.desc">Descrição de DVDEmpire</string>
		<string id="dvdempire.subcat">Categorias Adulto</string>
		<string id="dvdempire.details">Detalhes de Adultdvdempire.com</string>
		<string id="dvdempire.stars">Estrelas pornográficas</string>
		<string id="dvdempire.notice">Atores marcados em vermelho não estão no VCD-DB.&lt;br/&gt;Mas você pode marcar seus nomes e eles serão adicionados automaticamente no VCD-db e associados com este filme.</string>
		<string id="dvdempire.fetch">Trazer também</string>


		<!-- strings for the loan system -->
		<string id="loan.movies">Filmes para emprestar</string>
		<string id="loan.to">Emprestar filmes para</string>
		<string id="loan.addusers">Adicione alguns usuários para empréstimo para continuar</string>
		<string id="loan.newuser">Novo emprestador</string>
		<string id="loan.registeruser">Adicionar novo emprestador</string>
		<string id="loan.name">Nome</string>
		<string id="loan.select">Selecione emprestador</string>
		<string id="loan.movieloans">Filmes emprestados ...</string>
		<string id="loan.reminder">Enviar um lembrete</string>
		<string id="loan.history">Histórico de empréstimos</string>
		<string id="loan.history2">Ver histórico de empréstimos</string>
		<string id="loan.since">Desde</string>
		<string id="loan.time">Tempo desde</string>
		<string id="loan.return">Retornar cópia</string>
		<string id="loan.success">Filmes emprestados com sucesso</string>
		<string id="loan.out">Não retornou</string>
		<string id="loan.datein">Data de entrada</string>
		<string id="loan.dateout">Data de saída</string>
		<string id="loan.period">Período de empréstimo</string>
		<string id="loan.back">Voltar para o índice de empréstimos</string>
		<string id="loan.day">dia</string>
		<string id="loan.days">dias</string>
		<string id="loan.today">de hoje</string>


		<!-- strings for the RSS actions and settings -->
		<string id="rss.rss">Feeds RSS</string>
		<string id="rss.title">Feeds RSS de sites VCD-DB de amigos</string>
		<string id="rss.site">Feed RSS do Site</string>
		<string id="rss.user">Feed RSS do Usuário</string>
		<string id="rss.view">Ver feed RSS</string>
		<string id="rss.add">Adicionar novo feed</string>
		<string id="rss.note">Entre com a &lt;strong&gt;url exata&lt;/strong&gt; da base de dados de VCD dos seus amigos. Se RSS estiver disponível nos sites de seus amigos, você pode escolher os feeds que estiver interessado em exibir na sua página.</string>
		<string id="rss.fetch">Trazer Lista RSS</string>
		<string id="rss.none">Nenhum feed RSS foi adicionado.</string>
		<string id="rss.found">Os seguintes feeds RSS foram encontrados, selecione os feeds que você quer adicionar:</string>
		<string id="rss.notfound">Nenhum feed foi encontrado nesta localização</string>


		<!-- strings for the comments -->
		<string id="comments.comments">Comentários</string>
		<string id="comments.add">Postar novo comentário</string>
		<string id="comments.none">Nenhum comentário foi postado</string>
		<string id="comments.type">Digite seu novo comentário</string>
		<string id="comments.your">Seu comentário</string>
		<string id="comments.post">Postar comentário</string>
		<string id="comments.error">Você precisa estar logado para postar comentários</string>


		<!-- strings for the wishlist -->
		<string id="wishlist.add">Adicionar à minha lista de desejos</string>
		<string id="wishlist.onlist">Está na sua lista de desejos</string>
		<string id="wishlist.empty">Sua lista de desejos está vazia</string>
		<string id="wishlist.own">Eu possuo uma cópia deste filme</string>
		<string id="wishlist.notown">Eu não possuo uma cópia deste filme</string>


		<!-- strings for the pornstar entries -->
		<string id="pornstar.name">Nome</string>
		<string id="pornstar.web">Site Web</string>
		<string id="pornstar.moviecount">Contar filmes</string>


		<!-- strings for the "seen movies" page -->
		<string id="seen.seenit">Eu já ví este</string>
		<string id="seen.notseenit">Eu não ví este</string>
		<string id="seen.seenitclick">Clique para marcar como visto</string>
		<string id="seen.notseenitclick">Clique para marcar como não visto</string>


		<!-- strings for the statistics page -->
		<string id="statistics.title">Relatório de Hoje</string>
		<string id="statistics.top_movies">Filmes no banco de dados</string>
		<string id="statistics.top_cats">Categorias Top</string>
		<string id="statistics.top_act">Categorias mais ativas</string>
		<string id="statistics.top_covers">Capas no banco de dados</string>
		<string id="statistics.total">Total</string>
		<string id="statistics.today">Adicionados hoje</string>
		<string id="statistics.week">Adicionados nos últimos 7 dias</string>
		<string id="statistics.month">Adicionados nos últimos 30 dias</string>


		<!-- strings for the email messages sent from VCD-db -->
		<string id="mail.returntopic">Lembrete de empréstimo</string>
		<string id="mail.returnmovies1">%s, só gostaria de lembrá-lo de devolver meus filmes.&lt;br/&gt;Você ainda está com os seguintes filmes :&lt;br/&gt;&lt;br/&gt;</string>
		<string id="mail.returnmovies2">Por favor me devolva os discos o mais rápido possível&lt;br/&gt;Saudações %s&lt;br/&gt;&lt;br/&gt;nb. este é um e-mail automático do sistema VCD-db (http://vcddb.konni.com)</string>
		<string id="mail.notify">&lt;strong&gt;Um novo filme foi adicionado em VCD-db&lt;/strong&gt;&lt;br/&gt;Clique &lt;a href=&quot;%s/?page=cd&amp;vcd_id=%s&quot;&gt;aquí&lt;/a&gt; para ver mais...&lt;br/&gt;&lt;br/&gt;&lt;p&gt;nb. este é um e-mail automático do sistema VCD-db (vcddb.konni.com)&lt;/p&gt;</string>
		<string id="mail.register">%s, seu registro no VCD-db foi bem sucedido.&lt;br/&gt;&lt;br/&gt;Seu usuário é %s e sua senha é %s.&lt;br/&gt;&lt;br/&gt;Você sempre pode alterar a sua senha após estar logado.&lt;br/&gt;Clique &lt;a href=&quot;%s&quot; target=&quot;_new&quot;&gt;aquí&lt;/a&gt; para ir ao site VCD-db.</string>


		<!-- strings for the metadata -->
		<string id="metadata.my">Meus Metadados</string>
		<string id="metadata.name">Nome</string>
		<string id="metadata.desc">Descrição</string>
		<string id="metadata.type">Tipo Meta</string>
		<string id="metadata.value">Valor Meta</string>
		<string id="metadata.none">Não existe Metadata.</string>


		<!-- strings for the player settings and actions -->
		<string id="player.player">Tocador</string>
		<string id="player.path">Caminho</string>


		<!-- Miscelaneos strings that do not need specific category and/or are often used around VCD-db -->
		<string id="misc.contains">contém</string>
		<string id="misc.grade">Classificação IMDB maior que</string>
		<string id="misc.any">Qualquer</string>
		<string id="misc.tryagain">Tente novamente</string>
		<string id="misc.proceed">Prosseguir</string>
		<string id="misc.select">Selecionar</string>
		<string id="misc.confirm">Confirmar</string>
		<string id="misc.cancel">Cancelar</string>
		<string id="misc.attention">Atenção!</string>
		<string id="misc.status">Status</string>
		<string id="misc.success">Sucesso</string>
		<string id="misc.failure">Falha</string>
		<string id="misc.yes">Sim</string>
		<string id="misc.no">Não</string>
		<string id="misc.showmore">Mostrar mais</string>
		<string id="misc.showless">Mostrar menos</string>
		<string id="misc.new">Novo</string>
		<string id="misc.change">Alterar</string>
		<string id="misc.delete">Deletar</string>
		<string id="misc.update">Atualizar</string>
		<string id="misc.saveandclose">Salvar e fechar</string>
		<string id="misc.close">Fechar</string>
		<string id="misc.edit">Editar</string>
		<string id="misc.results">Resultados</string>
		<string id="misc.latestmovies">últimos filmes</string>
		<string id="misc.latesttv">últimos shows de TV</string>
		<string id="misc.latestblue">últimos X-rated</string>
		<string id="misc.movies">filmes</string>
		<string id="misc.nocats">Nenhum filme foi adicionado.</string>
		<string id="misc.nousers">Não existem usuários ativos</string>
		<string id="misc.key">Chave</string>
		<string id="misc.savenext">Salvar e editar próximo</string>
		<string id="misc.save">Salvar</string>
		<string id="misc.seen">Visto</string>
		<string id="misc.footer">Página Carregada em %s seg. (&lt;i&gt;%d Queries&lt;/I&gt;) &amp;nbsp; Copyright (c)</string>
		<string id="misc.footer_link">Conheça o site oficial do VCD-db</string>
		<string id="misc.toggle">Ativar pré-visualização</string>
		<string id="misc.toggle_on">ligado</string>
		<string id="misc.toggle_off">desligado</string>
	</strings>
</language>
